wpcord/__init__.py
wpcord/bot.py
wpcord/cdn.py
wpcord/channel.py
wpcord/client.py
wpcord/components.py
wpcord/embed.py
wpcord/emoji.py
wpcord/enums.py
wpcord/events.py
wpcord/exceptions.py
wpcord/file.py
wpcord/flags.py
wpcord/gateway.py
wpcord/guild.py
wpcord/http.py
wpcord/main.py
wpcord/member.py
wpcord/message.py
wpcord/object.py
wpcord/role.py
wpcord/snowflake.py
wpcord/unions.py
wpcord/user.py
wpcord/utils.py
wpcord/api/__init__.py
wpcord/api/__routes__.py
wpcord/api/application_commands.py
wpcord/api/channel.py
wpcord/api/guild.py
wpcord/api/receiving_and_responding.py
wpcord/api/user.py
wpcord/wp/__init__.py
wpcord/wp/enum.py
wpcord/wp/exceptions.py
wpcord/wp/flag.py
wpcord/wp/http.py
wpcord/wp/utils.py
wpcord-0.1.1.dist-info/LICENSE.txt
wpcord-0.1.1.dist-info/METADATA
wpcord-0.1.1.dist-info/WHEEL
wpcord-0.1.1.dist-info/top_level.txt
wpcord-0.1.1.dist-info/RECORD
