Metadata-Version: 2.1
Name: wpcord
Version: 0.1.1
Summary: A package for interacting with Discord API and Discord Gateway, also for making Discord Bots
Author: Willious Dark
Author-email: willious.dark@gmail.com
License: MIT
Classifier: Programming Language :: Python :: 3
Classifier: License :: OSI Approved :: MIT License
Classifier: Operating System :: OS Independent
License-File: LICENSE.txt
